testino.py
testino-0.3.14.dist-info/LICENSE
testino-0.3.14.dist-info/METADATA
testino-0.3.14.dist-info/WHEEL
testino-0.3.14.dist-info/top_level.txt
testino-0.3.14.dist-info/RECORD
